<?xml version="1.0" encoding="UTF-8"?>
<objects serializationModel="Studio.02.02.00">
	<object class="AudioFile" id="{ee9e4500-2132-4901-9073-b7bfc248126e}">
		<property name="assetPath">
			<value>SFX/Driving/sfx_CarLands2_JacobDickermanAndJacksonRichmond.wav</value>
		</property>
		<property name="frequencyInKHz">
			<value>48</value>
		</property>
		<property name="channelCount">
			<value>2</value>
		</property>
		<property name="length">
			<value>0.23258333333333334</value>
		</property>
		<relationship name="masterAssetFolder">
			<destination>{e03df7e9-f250-4d44-bfa2-667dce10cef1}</destination>
		</relationship>
	</object>
</objects>
